pydeps2env/__init__.py
pydeps2env/compressed_mapping.json
pydeps2env/environment.py
pydeps2env/generate_environment.py
pydeps2env-1.4.1.dist-info/licenses/LICENSE
test/test_package/pyproject.toml
test/test_package/testproject/__init__.py
pydeps2env-1.4.1.dist-info/METADATA
pydeps2env-1.4.1.dist-info/WHEEL
pydeps2env-1.4.1.dist-info/entry_points.txt
pydeps2env-1.4.1.dist-info/top_level.txt
pydeps2env-1.4.1.dist-info/RECORD
