Metadata-Version: 2.4
Name: pydeps2env
Version: 1.4.1
Summary: A python helper to generate conda environment files from project dependencies.
Author-email: Çağtay Fabry <cagtay.fabry@bam.de>
License-Expression: BSD-3-Clause
Project-URL: bug_tracker, https://github.com/CagtayFabry/pydeps2env/-/issues
Project-URL: repository, https://github.com/CagtayFabry/pydeps2env
Keywords: conda,pyproject
Classifier: Development Status :: 3 - Alpha
Classifier: Intended Audience :: Science/Research
Classifier: Natural Language :: English
Classifier: Operating System :: OS Independent
Classifier: Programming Language :: Python
Classifier: Programming Language :: Python :: 3 :: Only
Classifier: Programming Language :: Python :: 3.9
Classifier: Programming Language :: Python :: 3.10
Classifier: Programming Language :: Python :: 3.11
Classifier: Programming Language :: Python :: 3.12
Classifier: Programming Language :: Python :: 3.13
Requires-Python: >=3.9
License-File: LICENSE
Requires-Dist: packaging
Requires-Dist: pyyaml
Requires-Dist: tomli; python_version < "3.11"
Provides-Extra: test
Requires-Dist: pytest; extra == "test"
Requires-Dist: pytest-cov; extra == "test"
Dynamic: license-file
